spark_llm/__init__.py
spark_llm/cache.py
spark_llm/code_logger.py
spark_llm/file_cache.py
spark_llm/llm_chain_with_cache.py
spark_llm/llm_utils.py
spark_llm/prompt.py
spark_llm/search_tool_with_cache.py
spark_llm/spark_llm_assistant.py
spark_llm-0.1.9.dist-info/LICENSE
spark_llm-0.1.9.dist-info/METADATA
spark_llm-0.1.9.dist-info/WHEEL
spark_llm-0.1.9.dist-info/RECORD
