Metadata-Version: 2.1
Name: spark-llm
Version: 0.1.9
Summary: LLM assistant for the development of Spark applications
Home-page: https://github.com/gengliangwang/spark-llm
License: Apache-2.0
Author: Gengliang Wang
Author-email: gengliang@apache.org
Requires-Python: >=3.8.1,<4.0.0
Classifier: Development Status :: 3 - Alpha
Classifier: Intended Audience :: Developers
Classifier: License :: OSI Approved :: Apache Software License
Classifier: Programming Language :: Python :: 3
Classifier: Programming Language :: Python :: 3.9
Classifier: Programming Language :: Python :: 3.10
Classifier: Programming Language :: Python :: 3.11
Classifier: Programming Language :: Python :: 3
Classifier: Programming Language :: Python :: 3.10
Classifier: Programming Language :: Python :: 3.8
Classifier: Programming Language :: Python :: 3.9
Requires-Dist: beautifulsoup4 (>=4.12.2,<5.0.0)
Requires-Dist: google-api-python-client (>=2.90.0,<3.0.0)
Requires-Dist: langchain (>=0.0.201,<0.0.202)
Requires-Dist: openai (>=0.27.8,<0.28.0)
Requires-Dist: pandas (>=2.0.2,<3.0.0)
Requires-Dist: pygments (>=2.15.1,<3.0.0)
Requires-Dist: pyspark (>=3.4.0,<4.0.0)
Requires-Dist: requests (>=2.31.0,<3.0.0)
Requires-Dist: tiktoken (==0.4.0)
